{
  "ret": 0,
  "msg": null,
  "data": {
    "company_user": {
      "id": "43",
      "company_id": "5",
      "company_name": "NC\u79d1\u6280",
      "user_id": "38",
      "user_name": "Bob",
      "user_no": "",
      "first_char": "Bob",
      "user_pic": null,
      "user_phone": "",
      "user_mobile": "12345678910",
      "user_email": "",
      "user_gender": "M",
      "user_gender_name": "\u7537",
      "is_married_id": "0",
      "is_married_name": "\u5df2\u5a5a",
      "id_card_no": "12345678911",
      "address": "\u9655\u897f\u897f\u5b89",
      "birthday": "631152000",
      "hire_date": "1512777600",
      "age": "0",
      "position_id": null,
      "position_name": null,
      "position_level_id": null,
      "position_level_name": null,
      "education_level_id": "0",
      "education_level_name": "\u65e0",
      "emergency_contact": "",
      "emergency_phone": "",
      "description": "",
      "is_builder": "1",
      "is_default": "0",
      "status_id": "1",
      "status_name": "\u542f\u7528",
      "status_change_date": "1512741367",
      "dept_id": "31",
      "dept_name": "\u79d1\u6280\u90e8",
      "dept_long_id": "31;",
      "dept_long_name": "\u79d1\u6280\u90e8;",
      "is_delete": "0",
      "last_login_date": "1513598483",
      "operator_id": "2",
      "operator_name": "dms",
      "operate_date": "1512833152"
    },
    "global_user": {
      "id": "38",
      "account": "12345678910",
      "name": "Bob",
      "pwd": "bd7228143809da25a23b5352574656ea",
      "client_id": "1",
      "salt": "sWk3ty",
      "create_date": "1512741367",
      "last_date": "1513598483",
      "last_client_id": "2",
      "last_ip": "1863527998",
      "last_ip_address": "[\"\u4e2d\u56fd\",\"\u9655\u897f\",\"\u897f\u5b89\",\"\"]",
      "note": null,
      "is_delete": "0"
    },
    "user_id": "38",
    "user_name": "Bob",
    "access_token": "MWY3NGU5N2Y1YWJjNDg4ODQ5NDZlMGZkYmZmMDBmY2Y",
    "client_id": "2",
    "client_secret": "Y2Y0ZTI4ZjhjYzAxMTA2MTQ0YjdiZGM3ODA1NDY4OTY",
    "company": {
      "id": "5",
      "name": "NC\u79d1\u6280",
      "first_char": "NCkj",
      "country": "\u4e2d\u56fd",
      "province": "\u5e7f\u4e1c",
      "city": "\u6df1\u5733",
      "county": "\u5357\u5c71\u533a",
      "address": "\u897f\u4e3d\u6843\u6e90\u6751",
      "is_delete": "0",
      "builder_id": "2",
      "builder_name": "dms",
      "build_date": "1508168293",
      "link_person": "dms",
      "link_phone": "15612341234",
      "logo_pic": "",
      "note": "\u8fd9\u662f\u7b2c\u4e8c\u4e2a\u516c\u53f8",
      "operator_id": "2",
      "operator_name": "dms",
      "operate_date": "1508340617"
    },
    "company_id": "5",
    "company_name": "NC\u79d1\u6280"
  },
  "time": "Tue Dec 19 2017 21:27:00 GMT+0800"
}